job_hive/__init__.py
job_hive/core.py
job_hive/group.py
job_hive/job.py
job_hive/logger.py
job_hive/queue/__init__.py
job_hive/queue/base.py
job_hive/queue/redis_queue.py
job_hive/utils.py
job_hive/work.py
job_hive-0.1.8.dist-info/LICENSE
job_hive-0.1.8.dist-info/METADATA
job_hive-0.1.8.dist-info/WHEEL
job_hive-0.1.8.dist-info/RECORD
