Metadata-Version: 2.3
Name: job-hive
Version: 0.1.8
Summary: 一个极简的分布式任务模块
Author: YUNHAI
Author-email: bybxbwg@foxmail.com
Requires-Python: >=3.10,<4.0
Classifier: Programming Language :: Python :: 3
Classifier: Programming Language :: Python :: 3.10
Classifier: Programming Language :: Python :: 3.11
Classifier: Programming Language :: Python :: 3.12
Classifier: Programming Language :: Python :: 3.13
Provides-Extra: redis
Requires-Dist: redis (>=6.4.0,<7.0.0) ; extra == "redis"
